[{"url":"https://api.github.com/repos/bigdata-mindstorms/d3-playground/issues/comments/173927968","html_url":"https://github.com/bigdata-mindstorms/d3-playground/issues/29#issuecomment-173927968","issue_url":"https://api.github.com/repos/bigdata-mindstorms/d3-playground/issues/29","id":173927968,"user":{"login":"shuairenchang","id":16576137,"avatar_url":"https://avatars.githubusercontent.com/u/16576137?v=3","gravatar_id":"","url":"https://api.github.com/users/shuairenchang","html_url":"https://github.com/shuairenchang","followers_url":"https://api.github.com/users/shuairenchang/followers","following_url":"https://api.github.com/users/shuairenchang/following{/other_user}","gists_url":"https://api.github.com/users/shuairenchang/gists{/gist_id}","starred_url":"https://api.github.com/users/shuairenchang/starred{/owner}{/repo}","subscriptions_url":"https://api.github.com/users/shuairenchang/subscriptions","organizations_url":"https://api.github.com/users/shuairenchang/orgs","repos_url":"https://api.github.com/users/shuairenchang/repos","events_url":"https://api.github.com/users/shuairenchang/events{/privacy}","received_events_url":"https://api.github.com/users/shuairenchang/received_events","type":"User","site_admin":false},"created_at":"2016-01-22T14:00:52Z","updated_at":"2016-01-22T14:00:52Z","body":"\r\n\r\n![default](https://cloud.githubusercontent.com/assets/16576137/12512483/97368858-c153-11e5-83a9-c25fffff7c82.png)\r\n"},{"url":"https://api.github.com/repos/bigdata-mindstorms/d3-playground/issues/comments/173933043","html_url":"https://github.com/bigdata-mindstorms/d3-playground/issues/29#issuecomment-173933043","issue_url":"https://api.github.com/repos/bigdata-mindstorms/d3-playground/issues/29","id":173933043,"user":{"login":"ontouchstart","id":951921,"avatar_url":"https://avatars.githubusercontent.com/u/951921?v=3","gravatar_id":"","url":"https://api.github.com/users/ontouchstart","html_url":"https://github.com/ontouchstart","followers_url":"https://api.github.com/users/ontouchstart/followers","following_url":"https://api.github.com/users/ontouchstart/following{/other_user}","gists_url":"https://api.github.com/users/ontouchstart/gists{/gist_id}","starred_url":"https://api.github.com/users/ontouchstart/starred{/owner}{/repo}","subscriptions_url":"https://api.github.com/users/ontouchstart/subscriptions","organizations_url":"https://api.github.com/users/ontouchstart/orgs","repos_url":"https://api.github.com/users/ontouchstart/repos","events_url":"https://api.github.com/users/ontouchstart/events{/privacy}","received_events_url":"https://api.github.com/users/ontouchstart/received_events","type":"User","site_admin":false},"created_at":"2016-01-22T14:22:49Z","updated_at":"2016-01-22T14:22:49Z","body":"@shuairenchang 这个GitHub网页没有d3 库，你应该在这里做：\r\n>\r\n请使用[playground](https://bigdata-mindstorms.github.io/d3-playground/) （建议另开一个窗口并排看）"},{"url":"https://api.github.com/repos/bigdata-mindstorms/d3-playground/issues/comments/173937412","html_url":"https://github.com/bigdata-mindstorms/d3-playground/issues/29#issuecomment-173937412","issue_url":"https://api.github.com/repos/bigdata-mindstorms/d3-playground/issues/29","id":173937412,"user":{"login":"shuairenchang","id":16576137,"avatar_url":"https://avatars.githubusercontent.com/u/16576137?v=3","gravatar_id":"","url":"https://api.github.com/users/shuairenchang","html_url":"https://github.com/shuairenchang","followers_url":"https://api.github.com/users/shuairenchang/followers","following_url":"https://api.github.com/users/shuairenchang/following{/other_user}","gists_url":"https://api.github.com/users/shuairenchang/gists{/gist_id}","starred_url":"https://api.github.com/users/shuairenchang/starred{/owner}{/repo}","subscriptions_url":"https://api.github.com/users/shuairenchang/subscriptions","organizations_url":"https://api.github.com/users/shuairenchang/orgs","repos_url":"https://api.github.com/users/shuairenchang/repos","events_url":"https://api.github.com/users/shuairenchang/events{/privacy}","received_events_url":"https://api.github.com/users/shuairenchang/received_events","type":"User","site_admin":false},"created_at":"2016-01-22T14:39:18Z","updated_at":"2016-01-22T14:39:18Z","body":"![2](https://cloud.githubusercontent.com/assets/16576137/12513485/f4ddc160-c158-11e5-8b3d-d6014e0ddc0b.png)\r\n"},{"url":"https://api.github.com/repos/bigdata-mindstorms/d3-playground/issues/comments/173938593","html_url":"https://github.com/bigdata-mindstorms/d3-playground/issues/29#issuecomment-173938593","issue_url":"https://api.github.com/repos/bigdata-mindstorms/d3-playground/issues/29","id":173938593,"user":{"login":"ontouchstart","id":951921,"avatar_url":"https://avatars.githubusercontent.com/u/951921?v=3","gravatar_id":"","url":"https://api.github.com/users/ontouchstart","html_url":"https://github.com/ontouchstart","followers_url":"https://api.github.com/users/ontouchstart/followers","following_url":"https://api.github.com/users/ontouchstart/following{/other_user}","gists_url":"https://api.github.com/users/ontouchstart/gists{/gist_id}","starred_url":"https://api.github.com/users/ontouchstart/starred{/owner}{/repo}","subscriptions_url":"https://api.github.com/users/ontouchstart/subscriptions","organizations_url":"https://api.github.com/users/ontouchstart/orgs","repos_url":"https://api.github.com/users/ontouchstart/repos","events_url":"https://api.github.com/users/ontouchstart/events{/privacy}","received_events_url":"https://api.github.com/users/ontouchstart/received_events","type":"User","site_admin":false},"created_at":"2016-01-22T14:44:11Z","updated_at":"2016-01-22T14:44:11Z","body":":+1: :100: "},{"url":"https://api.github.com/repos/bigdata-mindstorms/d3-playground/issues/comments/173984798","html_url":"https://github.com/bigdata-mindstorms/d3-playground/issues/29#issuecomment-173984798","issue_url":"https://api.github.com/repos/bigdata-mindstorms/d3-playground/issues/29","id":173984798,"user":{"login":"s3931132","id":16720466,"avatar_url":"https://avatars.githubusercontent.com/u/16720466?v=3","gravatar_id":"","url":"https://api.github.com/users/s3931132","html_url":"https://github.com/s3931132","followers_url":"https://api.github.com/users/s3931132/followers","following_url":"https://api.github.com/users/s3931132/following{/other_user}","gists_url":"https://api.github.com/users/s3931132/gists{/gist_id}","starred_url":"https://api.github.com/users/s3931132/starred{/owner}{/repo}","subscriptions_url":"https://api.github.com/users/s3931132/subscriptions","organizations_url":"https://api.github.com/users/s3931132/orgs","repos_url":"https://api.github.com/users/s3931132/repos","events_url":"https://api.github.com/users/s3931132/events{/privacy}","received_events_url":"https://api.github.com/users/s3931132/received_events","type":"User","site_admin":false},"created_at":"2016-01-22T17:26:31Z","updated_at":"2016-01-22T17:26:31Z","body":"```javascript\r\nconsole.log(d3.select(\"body\"));\r\nd3.select(\"body\").append(\"p\").html(\"I'm p_a.Don't touch me!\");\r\nd3.select(\"body\").append(\"p\").attr(\"id\",\"p_b\").html(\"I'm p_b.Can you catch me?Can you give me a red coat?\");\r\nconsole.log(d3.select(\"p#p_b\").style(\"color\",\"red\").text());\r\n```\r\n\r\n[select.js](https://github.com/bigdata-mindstorms/d3-playground/blob/gh-pages/Liangdq/2016/01/23/select.js)\r\n\r\n![1234](https://cloud.githubusercontent.com/assets/16720466/12517923/50bb7344-c170-11e5-86dc-c0ef3888673c.png)\r\n"},{"url":"https://api.github.com/repos/bigdata-mindstorms/d3-playground/issues/comments/173992614","html_url":"https://github.com/bigdata-mindstorms/d3-playground/issues/29#issuecomment-173992614","issue_url":"https://api.github.com/repos/bigdata-mindstorms/d3-playground/issues/29","id":173992614,"user":{"login":"ontouchstart","id":951921,"avatar_url":"https://avatars.githubusercontent.com/u/951921?v=3","gravatar_id":"","url":"https://api.github.com/users/ontouchstart","html_url":"https://github.com/ontouchstart","followers_url":"https://api.github.com/users/ontouchstart/followers","following_url":"https://api.github.com/users/ontouchstart/following{/other_user}","gists_url":"https://api.github.com/users/ontouchstart/gists{/gist_id}","starred_url":"https://api.github.com/users/ontouchstart/starred{/owner}{/repo}","subscriptions_url":"https://api.github.com/users/ontouchstart/subscriptions","organizations_url":"https://api.github.com/users/ontouchstart/orgs","repos_url":"https://api.github.com/users/ontouchstart/repos","events_url":"https://api.github.com/users/ontouchstart/events{/privacy}","received_events_url":"https://api.github.com/users/ontouchstart/received_events","type":"User","site_admin":false},"created_at":"2016-01-22T17:56:24Z","updated_at":"2016-01-22T17:56:24Z","body":"@s3931132 Good work :+1: \r\n\r\nThe link to the runnable URL for your test code is here: \r\n\r\nhttps://bigdata-mindstorms.github.io/d3-playground/#https://bigdata-mindstorms.github.io/d3-playground/Liangdq/2016/01/23/select.js\r\n\r\n(Can you see the pattern? :smile: )\r\n\r\n![screen shot 2016-01-22 at 12 56 01 pm](https://cloud.githubusercontent.com/assets/951921/12518596/84243982-c107-11e5-9ec1-5f87d983c0e3.png)\r\n"},{"url":"https://api.github.com/repos/bigdata-mindstorms/d3-playground/issues/comments/173993079","html_url":"https://github.com/bigdata-mindstorms/d3-playground/issues/29#issuecomment-173993079","issue_url":"https://api.github.com/repos/bigdata-mindstorms/d3-playground/issues/29","id":173993079,"user":{"login":"ontouchstart","id":951921,"avatar_url":"https://avatars.githubusercontent.com/u/951921?v=3","gravatar_id":"","url":"https://api.github.com/users/ontouchstart","html_url":"https://github.com/ontouchstart","followers_url":"https://api.github.com/users/ontouchstart/followers","following_url":"https://api.github.com/users/ontouchstart/following{/other_user}","gists_url":"https://api.github.com/users/ontouchstart/gists{/gist_id}","starred_url":"https://api.github.com/users/ontouchstart/starred{/owner}{/repo}","subscriptions_url":"https://api.github.com/users/ontouchstart/subscriptions","organizations_url":"https://api.github.com/users/ontouchstart/orgs","repos_url":"https://api.github.com/users/ontouchstart/repos","events_url":"https://api.github.com/users/ontouchstart/events{/privacy}","received_events_url":"https://api.github.com/users/ontouchstart/received_events","type":"User","site_admin":false},"created_at":"2016-01-22T17:58:23Z","updated_at":"2016-01-22T18:00:02Z","body":"You can also expand the object in the console.\r\n\r\n![screen shot 2016-01-22 at 12 57 05 pm](https://cloud.githubusercontent.com/assets/951921/12518636/b85634f8-c107-11e5-8268-bfdf0ab6cfd6.png)\r\n\r\n:arrow_down: \r\n\r\n![screen shot 2016-01-22 at 12 56 53 pm](https://cloud.githubusercontent.com/assets/951921/12518655/cc652fee-c107-11e5-80b3-179b81be73b0.png)\r\n\r\nThis is the best way to learn [DOM](https://developer.mozilla.org/en-US/docs/Web/API/Document_Object_Model)."},{"url":"https://api.github.com/repos/bigdata-mindstorms/d3-playground/issues/comments/174135699","html_url":"https://github.com/bigdata-mindstorms/d3-playground/issues/29#issuecomment-174135699","issue_url":"https://api.github.com/repos/bigdata-mindstorms/d3-playground/issues/29","id":174135699,"user":{"login":"chenyl123","id":16750302,"avatar_url":"https://avatars.githubusercontent.com/u/16750302?v=3","gravatar_id":"","url":"https://api.github.com/users/chenyl123","html_url":"https://github.com/chenyl123","followers_url":"https://api.github.com/users/chenyl123/followers","following_url":"https://api.github.com/users/chenyl123/following{/other_user}","gists_url":"https://api.github.com/users/chenyl123/gists{/gist_id}","starred_url":"https://api.github.com/users/chenyl123/starred{/owner}{/repo}","subscriptions_url":"https://api.github.com/users/chenyl123/subscriptions","organizations_url":"https://api.github.com/users/chenyl123/orgs","repos_url":"https://api.github.com/users/chenyl123/repos","events_url":"https://api.github.com/users/chenyl123/events{/privacy}","received_events_url":"https://api.github.com/users/chenyl123/received_events","type":"User","site_admin":false},"created_at":"2016-01-23T04:37:30Z","updated_at":"2016-01-23T04:37:30Z","body":"为什么console.info/error/warn没有效果啊\r\n![test2](https://cloud.githubusercontent.com/assets/16750302/12528344/ee335058-c1cd-11e5-938a-b667bbf11a01.png)\r\n![test2_1](https://cloud.githubusercontent.com/assets/16750302/12528345/0bc7a89e-c1ce-11e5-9302-d72958602014.png)\r\n\r\n"},{"url":"https://api.github.com/repos/bigdata-mindstorms/d3-playground/issues/comments/174143979","html_url":"https://github.com/bigdata-mindstorms/d3-playground/issues/29#issuecomment-174143979","issue_url":"https://api.github.com/repos/bigdata-mindstorms/d3-playground/issues/29","id":174143979,"user":{"login":"chenyl123","id":16750302,"avatar_url":"https://avatars.githubusercontent.com/u/16750302?v=3","gravatar_id":"","url":"https://api.github.com/users/chenyl123","html_url":"https://github.com/chenyl123","followers_url":"https://api.github.com/users/chenyl123/followers","following_url":"https://api.github.com/users/chenyl123/following{/other_user}","gists_url":"https://api.github.com/users/chenyl123/gists{/gist_id}","starred_url":"https://api.github.com/users/chenyl123/starred{/owner}{/repo}","subscriptions_url":"https://api.github.com/users/chenyl123/subscriptions","organizations_url":"https://api.github.com/users/chenyl123/orgs","repos_url":"https://api.github.com/users/chenyl123/repos","events_url":"https://api.github.com/users/chenyl123/events{/privacy}","received_events_url":"https://api.github.com/users/chenyl123/received_events","type":"User","site_admin":false},"created_at":"2016-01-23T05:24:28Z","updated_at":"2016-01-23T05:24:28Z","body":"为什么再次执行，style就不起作用了\r\n![test3](https://cloud.githubusercontent.com/assets/16750302/12528537/928e06c4-c1d4-11e5-998b-5339af2d7dec.png)\r\n"},{"url":"https://api.github.com/repos/bigdata-mindstorms/d3-playground/issues/comments/174156771","html_url":"https://github.com/bigdata-mindstorms/d3-playground/issues/29#issuecomment-174156771","issue_url":"https://api.github.com/repos/bigdata-mindstorms/d3-playground/issues/29","id":174156771,"user":{"login":"ontouchstart","id":951921,"avatar_url":"https://avatars.githubusercontent.com/u/951921?v=3","gravatar_id":"","url":"https://api.github.com/users/ontouchstart","html_url":"https://github.com/ontouchstart","followers_url":"https://api.github.com/users/ontouchstart/followers","following_url":"https://api.github.com/users/ontouchstart/following{/other_user}","gists_url":"https://api.github.com/users/ontouchstart/gists{/gist_id}","starred_url":"https://api.github.com/users/ontouchstart/starred{/owner}{/repo}","subscriptions_url":"https://api.github.com/users/ontouchstart/subscriptions","organizations_url":"https://api.github.com/users/ontouchstart/orgs","repos_url":"https://api.github.com/users/ontouchstart/repos","events_url":"https://api.github.com/users/ontouchstart/events{/privacy}","received_events_url":"https://api.github.com/users/ontouchstart/received_events","type":"User","site_admin":false},"created_at":"2016-01-23T07:26:03Z","updated_at":"2016-01-23T07:26:03Z","body":"因为你用了id：p#p_b 这个元素每页只有一个。第二次运行时，改成红色的只有原先第一个。第二个新加上的完全被忽略了。\n\n> On Jan 23, 2016, at 00:24, chenyl <notifications@github.com> wrote:\n> \n> 为什么再次执行，style就不起作用了\n> \n> \n> —\n> Reply to this email directly or view it on GitHub.\n> \n"},{"url":"https://api.github.com/repos/bigdata-mindstorms/d3-playground/issues/comments/174156947","html_url":"https://github.com/bigdata-mindstorms/d3-playground/issues/29#issuecomment-174156947","issue_url":"https://api.github.com/repos/bigdata-mindstorms/d3-playground/issues/29","id":174156947,"user":{"login":"ontouchstart","id":951921,"avatar_url":"https://avatars.githubusercontent.com/u/951921?v=3","gravatar_id":"","url":"https://api.github.com/users/ontouchstart","html_url":"https://github.com/ontouchstart","followers_url":"https://api.github.com/users/ontouchstart/followers","following_url":"https://api.github.com/users/ontouchstart/following{/other_user}","gists_url":"https://api.github.com/users/ontouchstart/gists{/gist_id}","starred_url":"https://api.github.com/users/ontouchstart/starred{/owner}{/repo}","subscriptions_url":"https://api.github.com/users/ontouchstart/subscriptions","organizations_url":"https://api.github.com/users/ontouchstart/orgs","repos_url":"https://api.github.com/users/ontouchstart/repos","events_url":"https://api.github.com/users/ontouchstart/events{/privacy}","received_events_url":"https://api.github.com/users/ontouchstart/received_events","type":"User","site_admin":false},"created_at":"2016-01-23T07:30:58Z","updated_at":"2016-01-23T07:30:58Z","body":"这和浏览器有关。你试试不同的浏览器看看。\n\n> On Jan 22, 2016, at 23:37, chenyl <notifications@github.com> wrote:\n> \n> 为什么console.info/error/warn没有效果啊\n> \n> \n> \n> —\n> Reply to this email directly or view it on GitHub.\n> \n"},{"url":"https://api.github.com/repos/bigdata-mindstorms/d3-playground/issues/comments/174159507","html_url":"https://github.com/bigdata-mindstorms/d3-playground/issues/29#issuecomment-174159507","issue_url":"https://api.github.com/repos/bigdata-mindstorms/d3-playground/issues/29","id":174159507,"user":{"login":"ontouchstart","id":951921,"avatar_url":"https://avatars.githubusercontent.com/u/951921?v=3","gravatar_id":"","url":"https://api.github.com/users/ontouchstart","html_url":"https://github.com/ontouchstart","followers_url":"https://api.github.com/users/ontouchstart/followers","following_url":"https://api.github.com/users/ontouchstart/following{/other_user}","gists_url":"https://api.github.com/users/ontouchstart/gists{/gist_id}","starred_url":"https://api.github.com/users/ontouchstart/starred{/owner}{/repo}","subscriptions_url":"https://api.github.com/users/ontouchstart/subscriptions","organizations_url":"https://api.github.com/users/ontouchstart/orgs","repos_url":"https://api.github.com/users/ontouchstart/repos","events_url":"https://api.github.com/users/ontouchstart/events{/privacy}","received_events_url":"https://api.github.com/users/ontouchstart/received_events","type":"User","site_admin":false},"created_at":"2016-01-23T08:03:24Z","updated_at":"2016-01-23T08:04:38Z","body":"@chenyl123 \r\n\r\n我又做了一个测试，改成了class, 结果也一样。\r\n\r\n实际原因是d3.select() 只选出了第一个元素，如果要都选出来，要用d3.selectAll().\r\n\r\n\r\n![image](https://cloud.githubusercontent.com/assets/951921/12529226/8bd33b80-c17d-11e5-9dc1-608803dd40f1.png)\r\n\r\n![image](https://cloud.githubusercontent.com/assets/951921/12529227/961f9fca-c17d-11e5-9fbf-874bc1201ec5.png)\r\n\r\n用id原则上是不合法的，但是d3.selectAll()还是都选出来了\r\n\r\n![image](https://cloud.githubusercontent.com/assets/951921/12529238/c560c7be-c17d-11e5-9b32-a58d85f2881e.png)\r\n\r\n"},{"url":"https://api.github.com/repos/bigdata-mindstorms/d3-playground/issues/comments/174170867","html_url":"https://github.com/bigdata-mindstorms/d3-playground/issues/29#issuecomment-174170867","issue_url":"https://api.github.com/repos/bigdata-mindstorms/d3-playground/issues/29","id":174170867,"user":{"login":"chenyl123","id":16750302,"avatar_url":"https://avatars.githubusercontent.com/u/16750302?v=3","gravatar_id":"","url":"https://api.github.com/users/chenyl123","html_url":"https://github.com/chenyl123","followers_url":"https://api.github.com/users/chenyl123/followers","following_url":"https://api.github.com/users/chenyl123/following{/other_user}","gists_url":"https://api.github.com/users/chenyl123/gists{/gist_id}","starred_url":"https://api.github.com/users/chenyl123/starred{/owner}{/repo}","subscriptions_url":"https://api.github.com/users/chenyl123/subscriptions","organizations_url":"https://api.github.com/users/chenyl123/orgs","repos_url":"https://api.github.com/users/chenyl123/repos","events_url":"https://api.github.com/users/chenyl123/events{/privacy}","received_events_url":"https://api.github.com/users/chenyl123/received_events","type":"User","site_admin":false},"created_at":"2016-01-23T10:47:55Z","updated_at":"2016-01-23T10:47:55Z","body":"嗯，知道了，谢谢 \r\n------------------ Original ------------------\r\nFrom: \"Sam Liu\"<notifications@github.com>\r\nDate: Sat, Jan 23, 2016 04:03 PM\r\nTo: \"bigdata-mindstorms/d3-playground\"<d3-playground@noreply.github.com>;\r\nCc: \"chenyl\"<chenyl@uxsino.com>;\r\nSubject: Re: [d3-playground] 2016/01/21 selector (#29)\r\n\r\n\r\n\r\n@chenyl123 \r\n \r\n我又做了一个测试，改成了class, 结果也一样。\r\n \r\n实际原因是d3.select() 只选出了第一个元素，如果要都选出来，要有d3.selectAll().\r\n \r\n\r\n \r\n\r\n \r\n用id原则上是不合法的，但是d3.selectAll()还是都选出来了\r\n \r\n\r\n \r\n&mdash;\r\nReply to this email directly or view it on GitHub."},{"url":"https://api.github.com/repos/bigdata-mindstorms/d3-playground/issues/comments/174206349","html_url":"https://github.com/bigdata-mindstorms/d3-playground/issues/29#issuecomment-174206349","issue_url":"https://api.github.com/repos/bigdata-mindstorms/d3-playground/issues/29","id":174206349,"user":{"login":"jabonzhang","id":16721080,"avatar_url":"https://avatars.githubusercontent.com/u/16721080?v=3","gravatar_id":"","url":"https://api.github.com/users/jabonzhang","html_url":"https://github.com/jabonzhang","followers_url":"https://api.github.com/users/jabonzhang/followers","following_url":"https://api.github.com/users/jabonzhang/following{/other_user}","gists_url":"https://api.github.com/users/jabonzhang/gists{/gist_id}","starred_url":"https://api.github.com/users/jabonzhang/starred{/owner}{/repo}","subscriptions_url":"https://api.github.com/users/jabonzhang/subscriptions","organizations_url":"https://api.github.com/users/jabonzhang/orgs","repos_url":"https://api.github.com/users/jabonzhang/repos","events_url":"https://api.github.com/users/jabonzhang/events{/privacy}","received_events_url":"https://api.github.com/users/jabonzhang/received_events","type":"User","site_admin":false},"created_at":"2016-01-23T17:36:59Z","updated_at":"2016-01-23T17:36:59Z","body":"console.log(d3.select(\"body\"));   \r\nd3.select(\"body\").\r\nappend(\"p\")\r\n.html(\"Good Good Study!!\");  \r\nd3.select(\"body\")\r\n.append(\"p\")\r\n.attr(\"id\",\"p_b\")\r\n.html(\"Day Day Up!!\");   \r\nconsole.log(d3.select(\"p#p_b\")\r\n.style(\"color\",\"red\")\r\n.style(\"font-size\",\"29px\")\r\n.text());"},{"url":"https://api.github.com/repos/bigdata-mindstorms/d3-playground/issues/comments/174206626","html_url":"https://github.com/bigdata-mindstorms/d3-playground/issues/29#issuecomment-174206626","issue_url":"https://api.github.com/repos/bigdata-mindstorms/d3-playground/issues/29","id":174206626,"user":{"login":"jabonzhang","id":16721080,"avatar_url":"https://avatars.githubusercontent.com/u/16721080?v=3","gravatar_id":"","url":"https://api.github.com/users/jabonzhang","html_url":"https://github.com/jabonzhang","followers_url":"https://api.github.com/users/jabonzhang/followers","following_url":"https://api.github.com/users/jabonzhang/following{/other_user}","gists_url":"https://api.github.com/users/jabonzhang/gists{/gist_id}","starred_url":"https://api.github.com/users/jabonzhang/starred{/owner}{/repo}","subscriptions_url":"https://api.github.com/users/jabonzhang/subscriptions","organizations_url":"https://api.github.com/users/jabonzhang/orgs","repos_url":"https://api.github.com/users/jabonzhang/repos","events_url":"https://api.github.com/users/jabonzhang/events{/privacy}","received_events_url":"https://api.github.com/users/jabonzhang/received_events","type":"User","site_admin":false},"created_at":"2016-01-23T17:41:03Z","updated_at":"2016-01-23T17:41:03Z","body":"![001](https://cloud.githubusercontent.com/assets/16721080/12531669/8408d130-c23b-11e5-810d-55ebe2f78712.png)\r\n"},{"url":"https://api.github.com/repos/bigdata-mindstorms/d3-playground/issues/comments/174206717","html_url":"https://github.com/bigdata-mindstorms/d3-playground/issues/29#issuecomment-174206717","issue_url":"https://api.github.com/repos/bigdata-mindstorms/d3-playground/issues/29","id":174206717,"user":{"login":"jabonzhang","id":16721080,"avatar_url":"https://avatars.githubusercontent.com/u/16721080?v=3","gravatar_id":"","url":"https://api.github.com/users/jabonzhang","html_url":"https://github.com/jabonzhang","followers_url":"https://api.github.com/users/jabonzhang/followers","following_url":"https://api.github.com/users/jabonzhang/following{/other_user}","gists_url":"https://api.github.com/users/jabonzhang/gists{/gist_id}","starred_url":"https://api.github.com/users/jabonzhang/starred{/owner}{/repo}","subscriptions_url":"https://api.github.com/users/jabonzhang/subscriptions","organizations_url":"https://api.github.com/users/jabonzhang/orgs","repos_url":"https://api.github.com/users/jabonzhang/repos","events_url":"https://api.github.com/users/jabonzhang/events{/privacy}","received_events_url":"https://api.github.com/users/jabonzhang/received_events","type":"User","site_admin":false},"created_at":"2016-01-23T17:42:34Z","updated_at":"2016-01-23T17:42:34Z","body":"console.log(d3.select(\"body\"));\r\nd3.select(\"body\")\r\n.append(\"p\")\r\n.html(\"Good Good Study!!\");\r\nd3.select(\"body\")\r\n.append(\"p\")\r\n.attr(\"id\",\"p_b\")\r\n.html(\"Day Day Up!!\");\r\nconsole.log(d3.selectAll(\"p#p_b\")\r\n.style(\"color\",\"red\")\r\n.style(\"font-size\",\"29px\")\r\n.text());"},{"url":"https://api.github.com/repos/bigdata-mindstorms/d3-playground/issues/comments/174206784","html_url":"https://github.com/bigdata-mindstorms/d3-playground/issues/29#issuecomment-174206784","issue_url":"https://api.github.com/repos/bigdata-mindstorms/d3-playground/issues/29","id":174206784,"user":{"login":"jabonzhang","id":16721080,"avatar_url":"https://avatars.githubusercontent.com/u/16721080?v=3","gravatar_id":"","url":"https://api.github.com/users/jabonzhang","html_url":"https://github.com/jabonzhang","followers_url":"https://api.github.com/users/jabonzhang/followers","following_url":"https://api.github.com/users/jabonzhang/following{/other_user}","gists_url":"https://api.github.com/users/jabonzhang/gists{/gist_id}","starred_url":"https://api.github.com/users/jabonzhang/starred{/owner}{/repo}","subscriptions_url":"https://api.github.com/users/jabonzhang/subscriptions","organizations_url":"https://api.github.com/users/jabonzhang/orgs","repos_url":"https://api.github.com/users/jabonzhang/repos","events_url":"https://api.github.com/users/jabonzhang/events{/privacy}","received_events_url":"https://api.github.com/users/jabonzhang/received_events","type":"User","site_admin":false},"created_at":"2016-01-23T17:43:32Z","updated_at":"2016-01-23T17:43:32Z","body":"\r\n![002](https://cloud.githubusercontent.com/assets/16721080/12531678/db085564-c23b-11e5-8ced-bc2e10b5a865.png)\r\n"},{"url":"https://api.github.com/repos/bigdata-mindstorms/d3-playground/issues/comments/174254205","html_url":"https://github.com/bigdata-mindstorms/d3-playground/issues/29#issuecomment-174254205","issue_url":"https://api.github.com/repos/bigdata-mindstorms/d3-playground/issues/29","id":174254205,"user":{"login":"lrl1225","id":16516871,"avatar_url":"https://avatars.githubusercontent.com/u/16516871?v=3","gravatar_id":"","url":"https://api.github.com/users/lrl1225","html_url":"https://github.com/lrl1225","followers_url":"https://api.github.com/users/lrl1225/followers","following_url":"https://api.github.com/users/lrl1225/following{/other_user}","gists_url":"https://api.github.com/users/lrl1225/gists{/gist_id}","starred_url":"https://api.github.com/users/lrl1225/starred{/owner}{/repo}","subscriptions_url":"https://api.github.com/users/lrl1225/subscriptions","organizations_url":"https://api.github.com/users/lrl1225/orgs","repos_url":"https://api.github.com/users/lrl1225/repos","events_url":"https://api.github.com/users/lrl1225/events{/privacy}","received_events_url":"https://api.github.com/users/lrl1225/received_events","type":"User","site_admin":false},"created_at":"2016-01-24T05:03:47Z","updated_at":"2016-01-24T05:03:47Z","body":"```javascript\r\nd3.select('body')\r\n  .append('p').html('<h1>Have a good time!<h1>')\r\n  .append('div').attr('id','div_id').html('<br><h2>Learn select from here!</h2>')\r\n  .style('background', '#115545')\r\n  .style('width', '600px')\r\n  .style('height', '220px')\r\n  .style('margin-left','10%')\r\n  .style('padding-left','5%')\r\n  .style('padding-top','5%')\r\n  .style('color','#12ff56')\r\n  .append('a').attr('href','https://developer.mozilla.org/en-US/docs/Web/API/Document/querySelector')\r\n  .html('<br><b>MDN Document.querySelector()</b>')\r\n  .style('color','yellow')\r\n  .append('a').attr('href','https://developer.mozilla.org/zh-CN/docs/Web/API/Document/querySelector')\r\n  .html('<b>(中文版)</b>')\r\n  .style('color','red')\r\n  .append('a').attr('href','https://github.com/mbostock/d3/wiki/Selections')\r\n  .html('<br><b>d3.select </b>')\r\n  .style('color','#ff8866')\r\n  .append('a').attr('href','https://github.com/mbostock/d3/wiki/%E9%80%89%E6%8B%A9%E5%99%A8')\r\n  .html('<b>(中文版)</b>')\r\n  .style('color','red');\r\n  console.log(d3.select('body'));\r\n  console.log(d3.select('p').html());\r\n  console.log(d3.select('p').text());\r\n  console.log(d3.select('a').html());\r\n  console.log(d3.select('a').text());\r\n  console.log(d3.select('div#div_id').text());\r\n```\r\n[select.js](https://github.com/bigdata-mindstorms/d3-playground/blob/gh-pages/lrl1225/2016/01/21/select.js)\r\n[test code](https://bigdata-mindstorms.github.io/d3-playground/#https://bigdata-mindstorms.github.io/d3-playground/lrl1225/2016/01/21/select.js)"},{"url":"https://api.github.com/repos/bigdata-mindstorms/d3-playground/issues/comments/174342584","html_url":"https://github.com/bigdata-mindstorms/d3-playground/issues/29#issuecomment-174342584","issue_url":"https://api.github.com/repos/bigdata-mindstorms/d3-playground/issues/29","id":174342584,"user":{"login":"yvonned0609","id":16404158,"avatar_url":"https://avatars.githubusercontent.com/u/16404158?v=3","gravatar_id":"","url":"https://api.github.com/users/yvonned0609","html_url":"https://github.com/yvonned0609","followers_url":"https://api.github.com/users/yvonned0609/followers","following_url":"https://api.github.com/users/yvonned0609/following{/other_user}","gists_url":"https://api.github.com/users/yvonned0609/gists{/gist_id}","starred_url":"https://api.github.com/users/yvonned0609/starred{/owner}{/repo}","subscriptions_url":"https://api.github.com/users/yvonned0609/subscriptions","organizations_url":"https://api.github.com/users/yvonned0609/orgs","repos_url":"https://api.github.com/users/yvonned0609/repos","events_url":"https://api.github.com/users/yvonned0609/events{/privacy}","received_events_url":"https://api.github.com/users/yvonned0609/received_events","type":"User","site_admin":false},"created_at":"2016-01-24T21:21:07Z","updated_at":"2016-01-24T21:21:07Z","body":"![2016-01-24 4 20 51](https://cloud.githubusercontent.com/assets/16404158/12539002/7812969c-c2b6-11e5-9b27-280e95595499.png)\r\n"},{"url":"https://api.github.com/repos/bigdata-mindstorms/d3-playground/issues/comments/174437109","html_url":"https://github.com/bigdata-mindstorms/d3-playground/issues/29#issuecomment-174437109","issue_url":"https://api.github.com/repos/bigdata-mindstorms/d3-playground/issues/29","id":174437109,"user":{"login":"chenxiaorong","id":16496669,"avatar_url":"https://avatars.githubusercontent.com/u/16496669?v=3","gravatar_id":"","url":"https://api.github.com/users/chenxiaorong","html_url":"https://github.com/chenxiaorong","followers_url":"https://api.github.com/users/chenxiaorong/followers","following_url":"https://api.github.com/users/chenxiaorong/following{/other_user}","gists_url":"https://api.github.com/users/chenxiaorong/gists{/gist_id}","starred_url":"https://api.github.com/users/chenxiaorong/starred{/owner}{/repo}","subscriptions_url":"https://api.github.com/users/chenxiaorong/subscriptions","organizations_url":"https://api.github.com/users/chenxiaorong/orgs","repos_url":"https://api.github.com/users/chenxiaorong/repos","events_url":"https://api.github.com/users/chenxiaorong/events{/privacy}","received_events_url":"https://api.github.com/users/chenxiaorong/received_events","type":"User","site_admin":false},"created_at":"2016-01-25T08:38:02Z","updated_at":"2016-01-27T19:49:35Z","body":"```JavaScript\r\nconsole.log(d3.select(\"body\"));\r\nd3.select(\"body\").append(\"div\").html(\"今天下了好大的雪，好高兴呢，第四次看见雪！！\").style(\"color\",\"red\");\r\nd3.select(\"body\").append(\"div\").attr(\"id\",\"div_Snow\").html(\"下雪很好，可是好冷（~ . ~）\").style(\"color\",\"blue\");\r\nconsole.log(d3.select(\"div#div_Snow\").text());\r\n```\r\n\r\n[test_Select .js](https://github.com/bigdata-mindstorms/d3-playground/blob/gh-pages/Liangdq/2016/01/23/select.js)\r\n\r\n\r\nChen Xiaorong, You used other people's code link (Did you see the Liangdq in the above line? ), \r\nWhere is your code ? and can you post your own link and test link here?\r\n\r\n"},{"url":"https://api.github.com/repos/bigdata-mindstorms/d3-playground/issues/comments/174489908","html_url":"https://github.com/bigdata-mindstorms/d3-playground/issues/29#issuecomment-174489908","issue_url":"https://api.github.com/repos/bigdata-mindstorms/d3-playground/issues/29","id":174489908,"user":{"login":"keeping-action","id":13746263,"avatar_url":"https://avatars.githubusercontent.com/u/13746263?v=3","gravatar_id":"","url":"https://api.github.com/users/keeping-action","html_url":"https://github.com/keeping-action","followers_url":"https://api.github.com/users/keeping-action/followers","following_url":"https://api.github.com/users/keeping-action/following{/other_user}","gists_url":"https://api.github.com/users/keeping-action/gists{/gist_id}","starred_url":"https://api.github.com/users/keeping-action/starred{/owner}{/repo}","subscriptions_url":"https://api.github.com/users/keeping-action/subscriptions","organizations_url":"https://api.github.com/users/keeping-action/orgs","repos_url":"https://api.github.com/users/keeping-action/repos","events_url":"https://api.github.com/users/keeping-action/events{/privacy}","received_events_url":"https://api.github.com/users/keeping-action/received_events","type":"User","site_admin":false},"created_at":"2016-01-25T12:25:37Z","updated_at":"2016-01-25T12:25:37Z","body":"```JavaScript\r\nd3.select('body').append('div').attr('id','first').append('p').html('this is first div');\r\n\r\nd3.select('body').append('div').attr('id','second').append('p').html('this is second div');\r\n\r\nd3.select('body').append('div').attr('id','third').append('p').html('this is third div');\r\n\r\nd3.select('body').append('div').attr('id','fourth').append('p').html('this is fourth div ');\r\n\r\nd3.select('body').selectAll('div')\r\n\r\n                 .filter(function(d,i){\r\n\r\n                    return i%2 !==0 ? true : false;\r\n\r\n                 })\r\n\r\n                 .each(function(d,i){\r\n\r\n                     console.log(d3.select(this).html());\r\n\r\n                 });\r\n\r\n\r\n```\r\n[selections.js](https://bigdata-mindstorms.github.io/d3-playground/#https://bigdata-mindstorms.github.io/d3-playground/keeping-action/core/selections.js)"},{"url":"https://api.github.com/repos/bigdata-mindstorms/d3-playground/issues/comments/174504755","html_url":"https://github.com/bigdata-mindstorms/d3-playground/issues/29#issuecomment-174504755","issue_url":"https://api.github.com/repos/bigdata-mindstorms/d3-playground/issues/29","id":174504755,"user":{"login":"ontouchstart","id":951921,"avatar_url":"https://avatars.githubusercontent.com/u/951921?v=3","gravatar_id":"","url":"https://api.github.com/users/ontouchstart","html_url":"https://github.com/ontouchstart","followers_url":"https://api.github.com/users/ontouchstart/followers","following_url":"https://api.github.com/users/ontouchstart/following{/other_user}","gists_url":"https://api.github.com/users/ontouchstart/gists{/gist_id}","starred_url":"https://api.github.com/users/ontouchstart/starred{/owner}{/repo}","subscriptions_url":"https://api.github.com/users/ontouchstart/subscriptions","organizations_url":"https://api.github.com/users/ontouchstart/orgs","repos_url":"https://api.github.com/users/ontouchstart/repos","events_url":"https://api.github.com/users/ontouchstart/events{/privacy}","received_events_url":"https://api.github.com/users/ontouchstart/received_events","type":"User","site_admin":false},"created_at":"2016-01-25T13:12:08Z","updated_at":"2016-01-25T13:12:08Z","body":"@keeping-action   :+1: "},{"url":"https://api.github.com/repos/bigdata-mindstorms/d3-playground/issues/comments/174508927","html_url":"https://github.com/bigdata-mindstorms/d3-playground/issues/29#issuecomment-174508927","issue_url":"https://api.github.com/repos/bigdata-mindstorms/d3-playground/issues/29","id":174508927,"user":{"login":"LivingProgram","id":16373135,"avatar_url":"https://avatars.githubusercontent.com/u/16373135?v=3","gravatar_id":"","url":"https://api.github.com/users/LivingProgram","html_url":"https://github.com/LivingProgram","followers_url":"https://api.github.com/users/LivingProgram/followers","following_url":"https://api.github.com/users/LivingProgram/following{/other_user}","gists_url":"https://api.github.com/users/LivingProgram/gists{/gist_id}","starred_url":"https://api.github.com/users/LivingProgram/starred{/owner}{/repo}","subscriptions_url":"https://api.github.com/users/LivingProgram/subscriptions","organizations_url":"https://api.github.com/users/LivingProgram/orgs","repos_url":"https://api.github.com/users/LivingProgram/repos","events_url":"https://api.github.com/users/LivingProgram/events{/privacy}","received_events_url":"https://api.github.com/users/LivingProgram/received_events","type":"User","site_admin":false},"created_at":"2016-01-25T13:26:18Z","updated_at":"2016-01-25T13:26:18Z","body":"what is this doing?\r\n```javascript\r\n\r\n                 .filter(function(d,i){\r\n\r\n                    return i%2 !==0 ? true : false;\r\n\r\n                 })\r\n\r\n                 .each(function(d,i){\r\n\r\n                     console.log(d3.select(this).html());\r\n\r\n                 });\r\n```"},{"url":"https://api.github.com/repos/bigdata-mindstorms/d3-playground/issues/comments/174510252","html_url":"https://github.com/bigdata-mindstorms/d3-playground/issues/29#issuecomment-174510252","issue_url":"https://api.github.com/repos/bigdata-mindstorms/d3-playground/issues/29","id":174510252,"user":{"login":"ontouchstart","id":951921,"avatar_url":"https://avatars.githubusercontent.com/u/951921?v=3","gravatar_id":"","url":"https://api.github.com/users/ontouchstart","html_url":"https://github.com/ontouchstart","followers_url":"https://api.github.com/users/ontouchstart/followers","following_url":"https://api.github.com/users/ontouchstart/following{/other_user}","gists_url":"https://api.github.com/users/ontouchstart/gists{/gist_id}","starred_url":"https://api.github.com/users/ontouchstart/starred{/owner}{/repo}","subscriptions_url":"https://api.github.com/users/ontouchstart/subscriptions","organizations_url":"https://api.github.com/users/ontouchstart/orgs","repos_url":"https://api.github.com/users/ontouchstart/repos","events_url":"https://api.github.com/users/ontouchstart/events{/privacy}","received_events_url":"https://api.github.com/users/ontouchstart/received_events","type":"User","site_admin":false},"created_at":"2016-01-25T13:32:30Z","updated_at":"2016-01-25T13:32:30Z","body":"@keeping-action please explain. :smile: "},{"url":"https://api.github.com/repos/bigdata-mindstorms/d3-playground/issues/comments/174512007","html_url":"https://github.com/bigdata-mindstorms/d3-playground/issues/29#issuecomment-174512007","issue_url":"https://api.github.com/repos/bigdata-mindstorms/d3-playground/issues/29","id":174512007,"user":{"login":"LivingProgram","id":16373135,"avatar_url":"https://avatars.githubusercontent.com/u/16373135?v=3","gravatar_id":"","url":"https://api.github.com/users/LivingProgram","html_url":"https://github.com/LivingProgram","followers_url":"https://api.github.com/users/LivingProgram/followers","following_url":"https://api.github.com/users/LivingProgram/following{/other_user}","gists_url":"https://api.github.com/users/LivingProgram/gists{/gist_id}","starred_url":"https://api.github.com/users/LivingProgram/starred{/owner}{/repo}","subscriptions_url":"https://api.github.com/users/LivingProgram/subscriptions","organizations_url":"https://api.github.com/users/LivingProgram/orgs","repos_url":"https://api.github.com/users/LivingProgram/repos","events_url":"https://api.github.com/users/LivingProgram/events{/privacy}","received_events_url":"https://api.github.com/users/LivingProgram/received_events","type":"User","site_admin":false},"created_at":"2016-01-25T13:38:58Z","updated_at":"2016-01-25T13:38:58Z","body":"```javascript\r\nconsole.log(d3.select('body'));\r\nd3.select('body').append('div').append('p').html(\"Github\").style('font-size', '4px');\r\nd3.select('body').append('div').append('p').html(\"Github\").style('font-size', '16px');\r\nd3.select('body').append('div').append('p').html(\"Github\").style('font-size', '64px');\r\nd3.select('body').append('div').append('p').html(\"Github\").style('font-size', '256px');\r\n```\r\n![image](https://cloud.githubusercontent.com/assets/16373135/12552201/41950428-c33e-11e5-9f34-cbd8bce78a01.png)\r\n[selections.js](https://github.com/bigdata-mindstorms/d3-playground/blob/gh-pages/LivingProgram/2016/01/25/Selections.js)\r\n[selections.js Playground](https://bigdata-mindstorms.github.io/d3-playground/#https://bigdata-mindstorms.github.io/d3-playground//LivingProgram/2016/01/25/selections.js)"},{"url":"https://api.github.com/repos/bigdata-mindstorms/d3-playground/issues/comments/174518542","html_url":"https://github.com/bigdata-mindstorms/d3-playground/issues/29#issuecomment-174518542","issue_url":"https://api.github.com/repos/bigdata-mindstorms/d3-playground/issues/29","id":174518542,"user":{"login":"double126","id":16147477,"avatar_url":"https://avatars.githubusercontent.com/u/16147477?v=3","gravatar_id":"","url":"https://api.github.com/users/double126","html_url":"https://github.com/double126","followers_url":"https://api.github.com/users/double126/followers","following_url":"https://api.github.com/users/double126/following{/other_user}","gists_url":"https://api.github.com/users/double126/gists{/gist_id}","starred_url":"https://api.github.com/users/double126/starred{/owner}{/repo}","subscriptions_url":"https://api.github.com/users/double126/subscriptions","organizations_url":"https://api.github.com/users/double126/orgs","repos_url":"https://api.github.com/users/double126/repos","events_url":"https://api.github.com/users/double126/events{/privacy}","received_events_url":"https://api.github.com/users/double126/received_events","type":"User","site_admin":false},"created_at":"2016-01-25T14:08:51Z","updated_at":"2016-01-25T14:08:51Z","body":"@keeping-action \r\nconsole打出的i%2 !==0个？\r\nfunction(d,i)，.filter .each什么意思？\r\n"},{"url":"https://api.github.com/repos/bigdata-mindstorms/d3-playground/issues/comments/174524044","html_url":"https://github.com/bigdata-mindstorms/d3-playground/issues/29#issuecomment-174524044","issue_url":"https://api.github.com/repos/bigdata-mindstorms/d3-playground/issues/29","id":174524044,"user":{"login":"ontouchstart","id":951921,"avatar_url":"https://avatars.githubusercontent.com/u/951921?v=3","gravatar_id":"","url":"https://api.github.com/users/ontouchstart","html_url":"https://github.com/ontouchstart","followers_url":"https://api.github.com/users/ontouchstart/followers","following_url":"https://api.github.com/users/ontouchstart/following{/other_user}","gists_url":"https://api.github.com/users/ontouchstart/gists{/gist_id}","starred_url":"https://api.github.com/users/ontouchstart/starred{/owner}{/repo}","subscriptions_url":"https://api.github.com/users/ontouchstart/subscriptions","organizations_url":"https://api.github.com/users/ontouchstart/orgs","repos_url":"https://api.github.com/users/ontouchstart/repos","events_url":"https://api.github.com/users/ontouchstart/events{/privacy}","received_events_url":"https://api.github.com/users/ontouchstart/received_events","type":"User","site_admin":false},"created_at":"2016-01-25T14:32:22Z","updated_at":"2016-01-25T14:32:22Z","body":"@double126 \r\n\r\n你运行一下那段代码，看看console.log 输出，然后再看看懂不懂。 :smile:"},{"url":"https://api.github.com/repos/bigdata-mindstorms/d3-playground/issues/comments/174524464","html_url":"https://github.com/bigdata-mindstorms/d3-playground/issues/29#issuecomment-174524464","issue_url":"https://api.github.com/repos/bigdata-mindstorms/d3-playground/issues/29","id":174524464,"user":{"login":"ontouchstart","id":951921,"avatar_url":"https://avatars.githubusercontent.com/u/951921?v=3","gravatar_id":"","url":"https://api.github.com/users/ontouchstart","html_url":"https://github.com/ontouchstart","followers_url":"https://api.github.com/users/ontouchstart/followers","following_url":"https://api.github.com/users/ontouchstart/following{/other_user}","gists_url":"https://api.github.com/users/ontouchstart/gists{/gist_id}","starred_url":"https://api.github.com/users/ontouchstart/starred{/owner}{/repo}","subscriptions_url":"https://api.github.com/users/ontouchstart/subscriptions","organizations_url":"https://api.github.com/users/ontouchstart/orgs","repos_url":"https://api.github.com/users/ontouchstart/repos","events_url":"https://api.github.com/users/ontouchstart/events{/privacy}","received_events_url":"https://api.github.com/users/ontouchstart/received_events","type":"User","site_admin":false},"created_at":"2016-01-25T14:34:02Z","updated_at":"2016-01-25T14:34:02Z","body":"谁上个运行[这个](https://bigdata-mindstorms.github.io/d3-playground/#https://bigdata-mindstorms.github.io/d3-playground/keeping-action/core/selections.js)后的console截屏？"},{"url":"https://api.github.com/repos/bigdata-mindstorms/d3-playground/issues/comments/174553322","html_url":"https://github.com/bigdata-mindstorms/d3-playground/issues/29#issuecomment-174553322","issue_url":"https://api.github.com/repos/bigdata-mindstorms/d3-playground/issues/29","id":174553322,"user":{"login":"s3931132","id":16720466,"avatar_url":"https://avatars.githubusercontent.com/u/16720466?v=3","gravatar_id":"","url":"https://api.github.com/users/s3931132","html_url":"https://github.com/s3931132","followers_url":"https://api.github.com/users/s3931132/followers","following_url":"https://api.github.com/users/s3931132/following{/other_user}","gists_url":"https://api.github.com/users/s3931132/gists{/gist_id}","starred_url":"https://api.github.com/users/s3931132/starred{/owner}{/repo}","subscriptions_url":"https://api.github.com/users/s3931132/subscriptions","organizations_url":"https://api.github.com/users/s3931132/orgs","repos_url":"https://api.github.com/users/s3931132/repos","events_url":"https://api.github.com/users/s3931132/events{/privacy}","received_events_url":"https://api.github.com/users/s3931132/received_events","type":"User","site_admin":false},"created_at":"2016-01-25T15:57:22Z","updated_at":"2016-01-25T15:57:22Z","body":"@double126 \r\n```javascript\r\n .filter(function(d,i){\r\n                    return i%2 !==0 ? true : false;\r\n                 })\r\n//.filter是过滤选择器,这段代码返回为true的索引对应的元素被选中，即选择\"索引\"为奇数\r\n//函数中的i代表selection中的元素索引，这里指4个div（即索引为0~3）；d代表当前传递的数据，这个函数中未使用d\r\n  .each(function(d,i){\r\n        console.log(d3.select(this).html());\r\n   });\r\n//相当于遍历每一个元素，对选中的元素集合中的每一个进行操作。\r\n```\r\n这是我的理解 也请教授指正\r\n![160125232814](https://cloud.githubusercontent.com/assets/16720466/12556128/47d58854-c3bf-11e5-9fa5-f27dae61a600.png)\r\n"},{"url":"https://api.github.com/repos/bigdata-mindstorms/d3-playground/issues/comments/174555012","html_url":"https://github.com/bigdata-mindstorms/d3-playground/issues/29#issuecomment-174555012","issue_url":"https://api.github.com/repos/bigdata-mindstorms/d3-playground/issues/29","id":174555012,"user":{"login":"s3931132","id":16720466,"avatar_url":"https://avatars.githubusercontent.com/u/16720466?v=3","gravatar_id":"","url":"https://api.github.com/users/s3931132","html_url":"https://github.com/s3931132","followers_url":"https://api.github.com/users/s3931132/followers","following_url":"https://api.github.com/users/s3931132/following{/other_user}","gists_url":"https://api.github.com/users/s3931132/gists{/gist_id}","starred_url":"https://api.github.com/users/s3931132/starred{/owner}{/repo}","subscriptions_url":"https://api.github.com/users/s3931132/subscriptions","organizations_url":"https://api.github.com/users/s3931132/orgs","repos_url":"https://api.github.com/users/s3931132/repos","events_url":"https://api.github.com/users/s3931132/events{/privacy}","received_events_url":"https://api.github.com/users/s3931132/received_events","type":"User","site_admin":false},"created_at":"2016-01-25T16:02:36Z","updated_at":"2016-01-25T16:02:36Z","body":"请问下教授 为什么选中的是div标签  console出来的却是p标签呢"}]